topsis/__init__.py
topsis/__main__.py
topsisSaksham_102218063-1.0.1.dist-info/LICENSE
topsisSaksham_102218063-1.0.1.dist-info/METADATA
topsisSaksham_102218063-1.0.1.dist-info/WHEEL
topsisSaksham_102218063-1.0.1.dist-info/entry_points.txt
topsisSaksham_102218063-1.0.1.dist-info/top_level.txt
topsisSaksham_102218063-1.0.1.dist-info/RECORD
